nameko_cloudant/__init__.py
nameko_cloudant/database_session.py
nameko_cloudant-0.1.7.dist-info/DESCRIPTION.rst
nameko_cloudant-0.1.7.dist-info/METADATA
nameko_cloudant-0.1.7.dist-info/RECORD
nameko_cloudant-0.1.7.dist-info/WHEEL
nameko_cloudant-0.1.7.dist-info/metadata.json
nameko_cloudant-0.1.7.dist-info/top_level.txt
nameko_cloudant-0.1.7.dist-info/zip-safe
