Metadata-Version: 2.0
Name: nameko-cloudant
Version: 0.1.7
Summary: A dependency for cloudant
Home-page: http://github.com/frisellcpl/nameko-cloudant
Author: frisellcpl
Author-email: johan@trell.se
License: Apache License, Version 2.0
Platform: UNKNOWN
Classifier: Programming Language :: Python
Classifier: Operating System :: MacOS :: MacOS X
Classifier: Operating System :: POSIX
Classifier: Programming Language :: Python :: 2
Classifier: Programming Language :: Python :: 2.7
Classifier: Programming Language :: Python :: 3
Classifier: Programming Language :: Python :: 3.3
Classifier: Programming Language :: Python :: 3.4
Classifier: Topic :: Internet
Classifier: Topic :: Software Development :: Libraries :: Python Modules
Classifier: Intended Audience :: Developers
Requires-Dist: nameko (==2.4.2)
Requires-Dist: cloudant (==2.3.0)
